cnt/__init__.py
cnt/rulebase/__init__.py
cnt/rulebase/const/__init__.py
cnt/rulebase/const/chinese_chars.py
cnt/rulebase/const/cjk_compatibility_ideographs.py
cnt/rulebase/const/delimiters.py
cnt/rulebase/const/digits.py
cnt/rulebase/const/english_chars.py
cnt/rulebase/const/utils.py
cnt/rulebase/const/whitespaces.py
cnt/rulebase/rules/__init__.py
cnt/rulebase/rules/interval_based_operations/__init__.py
cnt/rulebase/rules/interval_based_operations/basic_operation.py
cnt/rulebase/rules/interval_based_operations/builtin_application.py
cnt/rulebase/rules/interval_based_operations/interval_based_collector.py
cnt/rulebase/rules/interval_based_operations/interval_based_replacer.py
cnt/rulebase/rules/sentence_segmentation/__init__.py
cnt/rulebase/rules/sentence_segmentation/const.py
cnt/rulebase/rules/sentence_segmentation/sentence_segmenter.py
cnt/rulebase/workflow/__init__.py
cnt/rulebase/workflow/basic_workflow.py
cnt/rulebase/workflow/exact_match_labeler.py
cnt/rulebase/workflow/interval_labeler.py
cnt/rulebase/workflow/type_annotations.py
cnt.rulebase-0.12.0.dist-info/AUTHORS.rst
cnt.rulebase-0.12.0.dist-info/LICENSE
cnt.rulebase-0.12.0.dist-info/METADATA
cnt.rulebase-0.12.0.dist-info/WHEEL
cnt.rulebase-0.12.0.dist-info/top_level.txt
cnt.rulebase-0.12.0.dist-info/RECORD
